<?xml version="1.0" encoding="utf-8" ?>
<dwsync>
<file name="avatar1.jpg" server="syu4187300001.my3w.com" local="130083313680000000" remote="131707438200000000" Dst="0" />
<file name="avatar2.jpg" server="syu4187300001.my3w.com" local="130083313680000000" remote="131707438200000000" Dst="0" />
<file name="banner-bg.jpg" server="syu4187300001.my3w.com" local="130443674220000000" remote="131707438200000000" Dst="0" />
<file name="dummy.png" server="syu4187300001.my3w.com" local="130129505440000000" remote="131707438200000000" Dst="0" />
<file name="icon.png" server="syu4187300001.my3w.com" local="130438206280000000" remote="131707438200000000" Dst="0" />
<file name="imac.png" server="syu4187300001.my3w.com" local="130118249900000000" remote="131707438200000000" Dst="0" />
<file name="lines.png" server="syu4187300001.my3w.com" local="130075165200000000" remote="131707438200000000" Dst="0" />
<file name="logo.png" server="syu4187300001.my3w.com" local="130443730100000000" remote="131707438200000000" Dst="0" />
<file name="logo1.png" server="syu4187300001.my3w.com" local="130438364320000000" remote="131707438200000000" Dst="0" />
<file name="main_carousel_nav.png" server="syu4187300001.my3w.com" local="130075165200000000" remote="131707438200000000" Dst="0" />
<file name="marker.png" server="syu4187300001.my3w.com" local="130319390460000000" remote="131707438200000000" Dst="0" />
<file name="my_avatar.jpg" server="syu4187300001.my3w.com" local="130083313680000000" remote="131707438200000000" Dst="0" />
<file name="next-light.png" server="syu4187300001.my3w.com" local="130129508400000000" remote="131707438200000000" Dst="0" />
<file name="play-pause-light.png" server="syu4187300001.my3w.com" local="130129504980000000" remote="131707438200000000" Dst="0" />
<file name="preload_img.gif" server="syu4187300001.my3w.com" local="130075165200000000" remote="131707438200000000" Dst="0" />
<file name="prev-light.png" server="syu4187300001.my3w.com" local="130129505280000000" remote="131707438200000000" Dst="0" />
<file name="ribbon.png" server="syu4187300001.my3w.com" local="130111704520000000" remote="131707438200000000" Dst="0" />
<file name="slider_nav.png" server="syu4187300001.my3w.com" local="130075165800000000" remote="131707438200000000" Dst="0" />
<file name="team1.jpg" server="syu4187300001.my3w.com" local="130083312920000000" remote="131707438200000000" Dst="0" />
<file name="team2.jpg" server="syu4187300001.my3w.com" local="130083312920000000" remote="131707438200000000" Dst="0" />
<file name="team3.jpg" server="syu4187300001.my3w.com" local="130083312920000000" remote="131707438200000000" Dst="0" />
<file name="team4.jpg" server="syu4187300001.my3w.com" local="130083312920000000" remote="131707438200000000" Dst="0" />
<file name="team5.jpg" server="syu4187300001.my3w.com" local="130083312920000000" remote="131707438200000000" Dst="0" />
<file name="team6.jpg" server="syu4187300001.my3w.com" local="130083312920000000" remote="131707438200000000" Dst="0" />
<file name="timer.png" server="syu4187300001.my3w.com" local="129846448700000000" remote="131707438200000000" Dst="0" />
<file name="zoom.png" server="syu4187300001.my3w.com" local="130126529200000000" remote="131707438200000000" Dst="0" />
</dwsync>